pipecat_ai_typecast-0.0.1.dist-info/licenses/LICENSE
pipecat_typecast/__init__.py
pipecat_typecast/tts.py
pipecat_ai_typecast-0.0.1.dist-info/METADATA
pipecat_ai_typecast-0.0.1.dist-info/WHEEL
pipecat_ai_typecast-0.0.1.dist-info/top_level.txt
pipecat_ai_typecast-0.0.1.dist-info/RECORD
