Metadata-Version: 2.4
Name: pipecat-ai-typecast
Version: 0.0.1
Summary: Typecast is an AI text-to-speech API that converts text into lifelike, expressive speech in many languages.
Author-email: Neosapience <help@typecast.ai>
Maintainer-email: Neosapience <help@typecast.ai>
License-Expression: BSD-2-Clause
Project-URL: Homepage, https://typecast.ai
Project-URL: Documentation, https://typecast.ai/docs/overview
Project-URL: Source, https://github.com/neosapience/pipecat-typecast
Keywords: pipecat,text-to-speech,ai
Classifier: Development Status :: 5 - Production/Stable
Classifier: Intended Audience :: Developers
Classifier: Topic :: Multimedia :: Sound/Audio :: Speech
Classifier: Topic :: Scientific/Engineering :: Artificial Intelligence
Requires-Python: >=3.10
License-File: LICENSE
Requires-Dist: pipecat-ai>=0.0.94
Requires-Dist: aiohttp>=3.9.0
Requires-Dist: loguru>=0.7.0
Requires-Dist: pydantic>=2.0.0
Dynamic: license-file
